banf/__init__.py
banf/communicate/__init__.py
banf/communicate/db_inserter.py
banf/communicate/kafka_consumer.py
banf/communicate/mqtt_receiver.py
banf/communicate/mqtt_sender.py
banf/communicate/prometheus_sender.py
banf/communicate/s3_sender.py
banf/data_processing/__init__.py
banf/data_processing/preprocessing.py
banf/etc/__init__.py
banf/etc/bench.py
banf/etc/observe.py
banf/etc/pattern.py
banf-0.0.7.dist-info/METADATA
banf-0.0.7.dist-info/WHEEL
banf-0.0.7.dist-info/top_level.txt
banf-0.0.7.dist-info/RECORD
