Metadata-Version: 2.1
Name: banf
Version: 0.0.7
Summary: Python package for BANF Co., Ltd.
Author: BANF Co., Ltd.
Author-email: gwjeon@banf.co.kr
Keywords: tire sensor,mqtt,aws,BANF Co., Ltd.
Classifier: Intended Audience :: Developers
Classifier: Programming Language :: Python :: 3
Requires-Dist: bleach (>=6.0.0)
Requires-Dist: bokeh (>=3.1.1)
Requires-Dist: boto3 (>=1.26.154)
Requires-Dist: botocore (>=1.29.154)
Requires-Dist: certifi (>=2023.5.7)
Requires-Dist: charset-normalizer (>=3.1.0)
Requires-Dist: click (>=8.1.3)
Requires-Dist: cloudpickle (>=2.2.1)
Requires-Dist: colorcet (>=3.0.1)
Requires-Dist: contourpy (>=1.1.0)
Requires-Dist: cycler (>=0.11.0)
Requires-Dist: dask (>=2023.6.0)
Requires-Dist: datashader (>=0.15.0)
Requires-Dist: datashape (>=0.5.2)
Requires-Dist: fonttools (>=4.40.0)
Requires-Dist: fsspec (>=2023.6.0)
Requires-Dist: holoviews (>=1.16.2)
Requires-Dist: idna (>=3.4)
Requires-Dist: ipympl (>=0.9.3)
Requires-Dist: ipython-genutils (>=0.2.0)
Requires-Dist: ipywidgets (>=8.0.6)
Requires-Dist: jaraco.classes (>=3.2.3)
Requires-Dist: Jinja2 (>=3.1.2)
Requires-Dist: jmespath (>=1.0.1)
Requires-Dist: joblib (>=1.2.0)
Requires-Dist: jupyterlab-widgets (>=3.0.7)
Requires-Dist: keyring (>=24.2.0)
Requires-Dist: kiwisolver (>=1.4.4)
Requires-Dist: linkify-it-py (>=2.0.2)
Requires-Dist: llvmlite (>=0.40.1rc1)
Requires-Dist: locket (>=1.0.0)
Requires-Dist: Markdown (>=3.4.3)
Requires-Dist: markdown-it-py (>=2.2.0)
Requires-Dist: MarkupSafe (>=2.1.3)
Requires-Dist: matplotlib (>=3.7.1)
Requires-Dist: mdit-py-plugins (>=0.4.0)
Requires-Dist: mdurl (>=0.1.2)
Requires-Dist: more-itertools (>=9.1.0)
Requires-Dist: multipledispatch (>=0.6.0)
Requires-Dist: numba (>=0.57.0)
Requires-Dist: numpy (>=1.24.3)
Requires-Dist: pandas (>=2.0.2)
Requires-Dist: panel (>=1.1.0)
Requires-Dist: param (>=1.13.0)
Requires-Dist: partd (>=1.4.0)
Requires-Dist: Pillow (>=9.5.0)
Requires-Dist: pkginfo (>=1.9.6)
Requires-Dist: pyarrow (>=12.0.1)
Requires-Dist: pyct (>=0.5.0)
Requires-Dist: pyparsing (>=3.0.9)
Requires-Dist: pytz (>=2023.3)
Requires-Dist: pyviz-comms (>=2.3.2)
Requires-Dist: PyYAML (>=6.0)
Requires-Dist: readme-renderer (>=40.0)
Requires-Dist: requests (>=2.31.0)
Requires-Dist: requests-toolbelt (>=1.0.0)
Requires-Dist: rfc3986 (>=2.0.0)
Requires-Dist: rich (>=13.4.2)
Requires-Dist: s3transfer (>=0.6.1)
Requires-Dist: scikit-learn (>=1.2.2)
Requires-Dist: scipy (>=1.10.1)
Requires-Dist: tqdm (>=4.65.0)
Requires-Dist: twine (>=4.0.2)
Requires-Dist: tzdata (>=2023.3)
Requires-Dist: uc-micro-py (>=1.0.2)
Requires-Dist: urllib3 (>=1.26.16)
Requires-Dist: webencodings (>=0.5.1)
Requires-Dist: widgetsnbextension (>=4.0.7)
Requires-Dist: xarray (>=2023.5.0)
Requires-Dist: xyzservices (>=2023.5.0)
